pysoworks/__main__.py
pysoworks/about_dialog.py
pysoworks/about_dialog.ui
pysoworks/action_manager.py
pysoworks/assets/__init__.py
pysoworks/assets/app_icon.ico
pysoworks/assets/app_icon.xcf
pysoworks/assets/dark_palette.json
pysoworks/assets/icon_piezosystem.png
pysoworks/assets/images/app_icon.svg
pysoworks/assets/images/app_icon_brand.svg
pysoworks/assets/images/cl_toggle01.svg
pysoworks/assets/images/cl_toggle02.svg
pysoworks/assets/images/cl_toggle_switch.svg
pysoworks/assets/images/modsrc_toggle01.svg
pysoworks/assets/images/modsrc_toggle02.svg
pysoworks/assets/images/modsrc_toggle03.svg
pysoworks/assets/images/modsrc_toggle04.svg
pysoworks/assets/images/modsrc_toggle2_01.svg
pysoworks/assets/images/modsrc_toggle2_02.svg
pysoworks/assets/images/modsrc_toggle2_03.svg
pysoworks/assets/images/modsrc_toggle2_04.svg
pysoworks/assets/images/modsrc_toggle_switch.svg
pysoworks/assets/images/modsrc_toggle_switch2.svg
pysoworks/assets/images/nv200_controller_structure.svg
pysoworks/assets/images/nv200_controller_structure@2x.png
pysoworks/assets/images/nv200_controller_structure_dark@2x.png
pysoworks/assets/images/piezosystem_logo@2x.png
pysoworks/assets/images/piezosystem_logo_white@2x.png
pysoworks/assets/stylesheets/ads/close-button-black.svg
pysoworks/assets/stylesheets/ads/close-button-disabled.svg
pysoworks/assets/stylesheets/ads/close-button-white.svg
pysoworks/assets/stylesheets/ads/detach-button-black.svg
pysoworks/assets/stylesheets/ads/detach-button-disabled.svg
pysoworks/assets/stylesheets/ads/detach-button-white.svg
pysoworks/assets/stylesheets/ads/maximize-button-black.svg
pysoworks/assets/stylesheets/ads/maximize-button-white.svg
pysoworks/assets/stylesheets/ads/minimize-button-black.svg
pysoworks/assets/stylesheets/ads/minimize-button-focused.svg
pysoworks/assets/stylesheets/ads/minimize-button-white.svg
pysoworks/assets/stylesheets/ads/pin-button-horizontal-black.svg
pysoworks/assets/stylesheets/ads/pin-button-horizontal-white.svg
pysoworks-1.0.6.dist-info/METADATA
pysoworks-1.0.6.dist-info/WHEEL
pysoworks-1.0.6.dist-info/entry_points.txt
pysoworks-1.0.6.dist-info/RECORD
